nd_vq_vae/__init__.py
nd_vq_vae/attention_ndim.py
nd_vq_vae/base.py
nd_vq_vae/utils.py
nd_vq_vae/vqvae_ndim.py
nd_vq_vae-1.0.3.dist-info/LICENSE
nd_vq_vae-1.0.3.dist-info/METADATA
nd_vq_vae-1.0.3.dist-info/WHEEL
nd_vq_vae-1.0.3.dist-info/entry_points.txt
nd_vq_vae-1.0.3.dist-info/top_level.txt
nd_vq_vae-1.0.3.dist-info/RECORD
