Metadata-Version: 2.1
Name: nd_vq_vae
Version: 1.0.3
Summary: PyTorch Implementation of an N-Dimensional VQ-VAE by AdityaNG
Home-page: https://github.com/AdityaNG/nD_VQ_VAE/
Author: AdityaNG
License-File: LICENSE
Requires-Dist: torch>=2.0
Requires-Dist: torchvision
Requires-Dist: numpy
Requires-Dist: pytorch-lightning
Requires-Dist: einops
Provides-Extra: test
Requires-Dist: pytest; extra == "test"
Requires-Dist: coverage; extra == "test"
Requires-Dist: flake8; extra == "test"
Requires-Dist: black; extra == "test"
Requires-Dist: isort; extra == "test"
Requires-Dist: pytest-cov; extra == "test"
Requires-Dist: mypy; extra == "test"
Requires-Dist: gitchangelog; extra == "test"
Requires-Dist: mkdocs; extra == "test"
Requires-Dist: lark; extra == "test"
Requires-Dist: types-requests; extra == "test"
Requires-Dist: requests-mock; extra == "test"
Requires-Dist: setuptools>=65.5.0; extra == "test"
Requires-Dist: av; extra == "test"
